sittr.py
sittr-0.1.2.dist-info/METADATA
sittr-0.1.2.dist-info/WHEEL
sittr-0.1.2.dist-info/entry_points.txt
sittr-0.1.2.dist-info/RECORD
