Metadata-Version: 2.4
Name: sittr
Version: 0.1.2
Summary: sittr cli tool for agentsitter.ai
Requires-Python: >=3.13
Requires-Dist: typer>=0.16.0
